anywebsitevideomanna.py
anywebsitevideomanna-1.dist-info/METADATA
anywebsitevideomanna-1.dist-info/WHEEL
anywebsitevideomanna-1.dist-info/top_level.txt
anywebsitevideomanna-1.dist-info/RECORD
